flaskpress_flask_htmlbuilder-0.13-py3.6-nspkg.pth
flask_htmlbuilder/htmlbuilder.py
flaskpress_flask_htmlbuilder-0.13.dist-info/DESCRIPTION.rst
flaskpress_flask_htmlbuilder-0.13.dist-info/METADATA
flaskpress_flask_htmlbuilder-0.13.dist-info/metadata.json
flaskpress_flask_htmlbuilder-0.13.dist-info/namespace_packages.txt
flaskpress_flask_htmlbuilder-0.13.dist-info/RECORD
flaskpress_flask_htmlbuilder-0.13.dist-info/top_level.txt
flaskpress_flask_htmlbuilder-0.13.dist-info/WHEEL
